Classfile /C:/Users/User/Quick_Ref/Programming/Java/workspace/Chapter8/bin/inheritance/VIPCustomer.class
  Last modified 2022. 1. 2.; size 803 bytes
  MD5 checksum d42cd533170762f91dec9c7964aadee8
  Compiled from "VIPCustomer.java"
public class inheritance.VIPCustomer extends inheritance.Customer
  minor version: 0
  major version: 53
  flags: (0x0021) ACC_PUBLIC, ACC_SUPER
  this_class: #1                          // inheritance/VIPCustomer
  super_class: #3                         // inheritance/Customer
  interfaces: 0, fields: 2, methods: 2, attributes: 1
Constant pool:
   #1 = Class              #2             // inheritance/VIPCustomer
   #2 = Utf8               inheritance/VIPCustomer
   #3 = Class              #4             // inheritance/Customer
   #4 = Utf8               inheritance/Customer
   #5 = Utf8               agentID
   #6 = Utf8               I
   #7 = Utf8               saleRatio
   #8 = Utf8               D
   #9 = Utf8               <init>
  #10 = Utf8               (ILjava/lang/String;)V
  #11 = Utf8               Code
  #12 = Methodref          #3.#13         // inheritance/Customer."<init>":(ILjava/lang/String;)V
  #13 = NameAndType        #9:#10         // "<init>":(ILjava/lang/String;)V
  #14 = String             #15            // VIP
  #15 = Utf8               VIP
  #16 = Fieldref           #1.#17         // inheritance/VIPCustomer.customerGrade:Ljava/lang/String;
  #17 = NameAndType        #18:#19        // customerGrade:Ljava/lang/String;
  #18 = Utf8               customerGrade
  #19 = Utf8               Ljava/lang/String;
  #20 = Double             0.05d
  #22 = Fieldref           #1.#23         // inheritance/VIPCustomer.bonusRatio:D
  #23 = NameAndType        #24:#8         // bonusRatio:D
  #24 = Utf8               bonusRatio
  #25 = Double             0.1d
  #27 = Fieldref           #1.#28         // inheritance/VIPCustomer.saleRatio:D
  #28 = NameAndType        #7:#8          // saleRatio:D
  #29 = Fieldref           #30.#32        // java/lang/System.out:Ljava/io/PrintStream;
  #30 = Class              #31            // java/lang/System
  #31 = Utf8               java/lang/System
  #32 = NameAndType        #33:#34        // out:Ljava/io/PrintStream;
  #33 = Utf8               out
  #34 = Utf8               Ljava/io/PrintStream;
  #35 = String             #36            // VIPCustomer() 호출
  #36 = Utf8               VIPCustomer() 호출
  #37 = Methodref          #38.#40        // java/io/PrintStream.println:(Ljava/lang/String;)V
  #38 = Class              #39            // java/io/PrintStream
  #39 = Utf8               java/io/PrintStream
  #40 = NameAndType        #41:#42        // println:(Ljava/lang/String;)V
  #41 = Utf8               println
  #42 = Utf8               (Ljava/lang/String;)V
  #43 = Utf8               LineNumberTable
  #44 = Utf8               LocalVariableTable
  #45 = Utf8               this
  #46 = Utf8               Linheritance/VIPCustomer;
  #47 = Utf8               customerID
  #48 = Utf8               customerName
  #49 = Utf8               getAgentID
  #50 = Utf8               ()I
  #51 = Fieldref           #1.#52         // inheritance/VIPCustomer.agentID:I
  #52 = NameAndType        #5:#6          // agentID:I
  #53 = Utf8               SourceFile
  #54 = Utf8               VIPCustomer.java
{
  public inheritance.VIPCustomer(int, java.lang.String);
    descriptor: (ILjava/lang/String;)V
    flags: (0x0001) ACC_PUBLIC
    Code:
      stack=3, locals=3, args_size=3
         0: aload_0
         1: iload_1
         2: aload_2
         3: invokespecial #12                 // Method inheritance/Customer."<init>":(ILjava/lang/String;)V
         6: aload_0
         7: ldc           #14                 // String VIP
         9: putfield      #16                 // Field customerGrade:Ljava/lang/String;
        12: aload_0
        13: ldc2_w        #20                 // double 0.05d
        16: putfield      #22                 // Field bonusRatio:D
        19: aload_0
        20: ldc2_w        #25                 // double 0.1d
        23: putfield      #27                 // Field saleRatio:D
        26: getstatic     #29                 // Field java/lang/System.out:Ljava/io/PrintStream;
        29: ldc           #35                 // String VIPCustomer() 호출
        31: invokevirtual #37                 // Method java/io/PrintStream.println:(Ljava/lang/String;)V
        34: return
      LineNumberTable:
        line 10: 0
        line 11: 6
        line 12: 12
        line 13: 19
        line 15: 26
        line 16: 34
      LocalVariableTable:
        Start  Length  Slot  Name   Signature
            0      35     0  this   Linheritance/VIPCustomer;
            0      35     1 customerID   I
            0      35     2 customerName   Ljava/lang/String;

  public int getAgentID();
    descriptor: ()I
    flags: (0x0001) ACC_PUBLIC
    Code:
      stack=1, locals=1, args_size=1
         0: aload_0
         1: getfield      #51                 // Field agentID:I
         4: ireturn
      LineNumberTable:
        line 19: 0
      LocalVariableTable:
        Start  Length  Slot  Name   Signature
            0       5     0  this   Linheritance/VIPCustomer;
}
SourceFile: "VIPCustomer.java"
