Classfile /C:/Users/USER/Quick_Ref/Programming/Java/DO_it_Java_자바프로그래밍입문_박은종/workspace/java-start/bin/test/VIPCustomer.class
  Last modified 2023. 12. 5.; size 505 bytes
  SHA-256 checksum c1e9e30dd939d826a15ee12590d05d09a40717bf36f023cb1614b1bdfe7a8d3e
  Compiled from "VIPCustomer.java"
public class test.VIPCustomer extends test.Customer
  minor version: 0
  major version: 52
  flags: (0x0021) ACC_PUBLIC, ACC_SUPER
  this_class: #1                          // test/VIPCustomer
  super_class: #3                         // test/Customer
  interfaces: 0, fields: 1, methods: 1, attributes: 1
Constant pool:
   #1 = Class              #2             // test/VIPCustomer
   #2 = Utf8               test/VIPCustomer
   #3 = Class              #4             // test/Customer
   #4 = Utf8               test/Customer
   #5 = Utf8               saleRatio
   #6 = Utf8               D
   #7 = Utf8               <init>
   #8 = Utf8               (ILjava/lang/String;)V
   #9 = Utf8               Code
  #10 = Methodref          #3.#11         // test/Customer."<init>":(ILjava/lang/String;)V
  #11 = NameAndType        #7:#8          // "<init>":(ILjava/lang/String;)V
  #12 = String             #13            // VIP
  #13 = Utf8               VIP
  #14 = Fieldref           #1.#15         // test/VIPCustomer.customerGrade:Ljava/lang/String;
  #15 = NameAndType        #16:#17        // customerGrade:Ljava/lang/String;
  #16 = Utf8               customerGrade
  #17 = Utf8               Ljava/lang/String;
  #18 = Double             0.05d
  #20 = Fieldref           #1.#21         // test/VIPCustomer.bonusRatio:D
  #21 = NameAndType        #22:#6         // bonusRatio:D
  #22 = Utf8               bonusRatio
  #23 = Double             0.1d
  #25 = Fieldref           #1.#26         // test/VIPCustomer.saleRatio:D
  #26 = NameAndType        #5:#6          // saleRatio:D
  #27 = Utf8               LineNumberTable
  #28 = Utf8               LocalVariableTable
  #29 = Utf8               this
  #30 = Utf8               Ltest/VIPCustomer;
  #31 = Utf8               customerID
  #32 = Utf8               I
  #33 = Utf8               customerName
  #34 = Utf8               SourceFile
  #35 = Utf8               VIPCustomer.java
{
  public test.VIPCustomer(int, java.lang.String);
    descriptor: (ILjava/lang/String;)V
    flags: (0x0001) ACC_PUBLIC
    Code:
      stack=3, locals=3, args_size=3
         0: aload_0
         1: iload_1
         2: aload_2
         3: invokespecial #10                 // Method test/Customer."<init>":(ILjava/lang/String;)V
         6: aload_0
         7: ldc           #12                 // String VIP
         9: putfield      #14                 // Field customerGrade:Ljava/lang/String;
        12: aload_0
        13: ldc2_w        #18                 // double 0.05d
        16: putfield      #20                 // Field bonusRatio:D
        19: aload_0
        20: ldc2_w        #23                 // double 0.1d
        23: putfield      #25                 // Field saleRatio:D
        26: return
      LineNumberTable:
        line 8: 0
        line 9: 6
        line 10: 12
        line 11: 19
        line 12: 26
      LocalVariableTable:
        Start  Length  Slot  Name   Signature
            0      27     0  this   Ltest/VIPCustomer;
            0      27     1 customerID   I
            0      27     2 customerName   Ljava/lang/String;
}
SourceFile: "VIPCustomer.java"
